LICENSE
README.md
pyproject.toml
examples/__init__.py
examples/example1.py
fsm_finite_state_machine/__init__.py
fsm_finite_state_machine/fsm.py
fsm_finite_state_machine.egg-info/PKG-INFO
fsm_finite_state_machine.egg-info/SOURCES.txt
fsm_finite_state_machine.egg-info/dependency_links.txt
fsm_finite_state_machine.egg-info/entry_points.txt
fsm_finite_state_machine.egg-info/top_level.txt