Metadata-Version: 2.1
Name: fsm-finite-state-machine
Version: 0.1.0
Summary: Finite State Machine
Author-email: André Rodrigues Almeida <dralm3ida.dev@gmail.com>
License: MIT License
Project-URL: repository, https://github.com/dralm3ida/finite-state-machine
Keywords: fsm_finite_state_machine,setuptools
Classifier: License :: OSI Approved :: MIT License
Classifier: Programming Language :: Python
Classifier: Programming Language :: Python :: 3
Requires-Python: >=3.8
License-File: LICENSE
